socialpy/__about__.py
socialpy/__init__.py
socialpy/__main__.py
socialpy/funcs.py
socialpy/bot/__init__.py
socialpy/bot/__main__.py
socialpy/client/__init__.py
socialpy/client/__main__.py
socialpy/client/gateway.py
socialpy/client/apis/__init__.py
socialpy/client/apis/basic.py
socialpy/client/apis/facebook.py
socialpy/client/apis/instagram.py
socialpy/client/apis/twitter.py
socialpy/data/__init__.py
socialpy/data/__main__.py
socialpy/scripts/__init__.py
socialpy/scripts/twitter.py
socialpy/server/__init__.py
socialpy/server/__main__.py
socialpy/server/manage.py
socialpy/server/urls.py
socialpy/server/utils.py
socialpy/server/wsgi.py
socialpy/server/data/__init__.py
socialpy/server/data/admin.py
socialpy/server/data/apps.py
socialpy/server/data/models.py
socialpy/server/data/tests.py
socialpy/server/data/views.py
socialpy/server/data/migrations/0001_initial.py
socialpy/server/data/migrations/__init__.py
socialpy/server/rest/__init__.py
socialpy/server/rest/apps.py
socialpy/server/rest/serializers.py
socialpy/server/rest/tests.py
socialpy/server/rest/urls.py
socialpy/server/rest/views.py
socialpy/server/rest/migrations/__init__.py
socialpy/server/settings/__init__.py
socialpy/server/settings/base.py
socialpy/server/settings/data.py
socialpy/server/settings/development.py
socialpy/server/settings/local.py
socialpy/server/settings/server.py
socialpy-0.0.3.dist-info/METADATA
socialpy-0.0.3.dist-info/RECORD
socialpy-0.0.3.dist-info/WHEEL
socialpy-0.0.3.dist-info/entry_points.txt
socialpy-0.0.3.dist-info/top_level.txt
