Metadata-Version: 2.1
Name: socialpy
Version: 0.0.3
Summary: Use social networks like a hacke
Home-page: https://github.com/axju/socialpy
Author: Axel Juraske
Author-email: axel.juraske@short-report.de
License: MIT
Platform: UNKNOWN
Requires-Dist: tweepy
Requires-Dist: django
Requires-Dist: djangorestframework
Requires-Dist: coreapi
Requires-Dist: Pillow
Requires-Dist: tabulate
